Metadata-Version: 1.0
Name: hepo-probability
Version: 0.1
Summary: Gaussian and Binomial distributions
Home-page: UNKNOWN
Author: Eddie Palomino
Author-email: palomino.ochoah@gmail.com
License: UNKNOWN
Platform: UNKNOWN
